.DS_Store
image_search_colors/__init__.py
image_search_colors/image_search_average.py
image_search_colors/web_image_search.py
searchcolor/__init__.py
searchcolor/average.py
searchcolor/exceptions.py
searchcolor/web_image.py
searchcolor-2.1.3.dist-info/DESCRIPTION.rst
searchcolor-2.1.3.dist-info/METADATA
searchcolor-2.1.3.dist-info/RECORD
searchcolor-2.1.3.dist-info/WHEEL
searchcolor-2.1.3.dist-info/metadata.json
searchcolor-2.1.3.dist-info/top_level.txt
