Metadata-Version: 2.0
Name: searchcolor
Version: 2.1.3
Summary: Image color extraction from web image search
Home-page: https://github.com/Tathorack/searchcolor
Author: Rhys Hansen
Author-email: rhyshonline@gmail.com
License: MIT
Keywords: image average color search google
Platform: UNKNOWN
Classifier: Development Status :: 3 - Alpha
Classifier: License :: OSI Approved :: MIT License
Classifier: Programming Language :: Python :: 3
Classifier: Programming Language :: Python :: 3.5
Classifier: Intended Audience :: Other Audience
Classifier: Topic :: Artistic Software
Classifier: Topic :: Multimedia :: Graphics
Requires-Dist: google-api-python-client
Requires-Dist: imagecolor (>=1.0.0)
Requires-Dist: py-ms-cognitive
Requires-Dist: requests
